odoo10_addon_partner_coc-10.0.1.0.0-py2.7-nspkg.pth
odoo/addons/partner_coc/README.rst
odoo/addons/partner_coc/__init__.py
odoo/addons/partner_coc/__manifest__.py
odoo/addons/partner_coc/data/res_partner_id_category_data.xml
odoo/addons/partner_coc/models/__init__.py
odoo/addons/partner_coc/models/res_partner.py
odoo/addons/partner_coc/views/res_partner_view.xml
odoo10_addon_partner_coc-10.0.1.0.0.dist-info/DESCRIPTION.rst
odoo10_addon_partner_coc-10.0.1.0.0.dist-info/METADATA
odoo10_addon_partner_coc-10.0.1.0.0.dist-info/RECORD
odoo10_addon_partner_coc-10.0.1.0.0.dist-info/WHEEL
odoo10_addon_partner_coc-10.0.1.0.0.dist-info/metadata.json
odoo10_addon_partner_coc-10.0.1.0.0.dist-info/namespace_packages.txt
odoo10_addon_partner_coc-10.0.1.0.0.dist-info/top_level.txt
